fullmetalpandas/__init__.py
fullmetalpandas/records.py
fullmetalpandas/sqldataframe.py
fullmetalpandas/sqltable.py
fullmetalpandas-0.1.1.dist-info/LICENSE
fullmetalpandas-0.1.1.dist-info/METADATA
fullmetalpandas-0.1.1.dist-info/WHEEL
fullmetalpandas-0.1.1.dist-info/top_level.txt
fullmetalpandas-0.1.1.dist-info/RECORD
